{
  "dataType": 1,
  "name": "Pistol",
  "catagory": "Weapons Ranged",
  "description": "a small fire arm that packs quite a punch for its size. hard to control and eats ammo for breakfast",
  "infoContainer": {
    "MainStatBody": 0,
    "MainStatConviction": 0,
    "MainStatCunning": 0,
    "MainStatPassion": 0,
    "MainStatReason": 0,
    "MainStatProwess": 0,
    "MainStatFate": 0,
    "MainStatFocus": 0,
    "SkillAthletics": 0,
    "SkillAuthority": 0,
    "SkillLogic": 0,
    "SkillPanache": 0,
    "SkillPerception": 0,
    "SkillResolve": 0,
    "SkillCrafts": 0,
    "SkillKeening": 0,
    "SkillKnowledge": 0,
    "SkillMedicine": 0,
    "SkillStealth": 0,
    "SkillSurvival": 0,
    "SkillArchery": 0,
    "SkillFight": 0,
    "SkillMarksmanship": 0,
    "SkillMelee": 0,
    "SkillGenericNatural": 0,
    "SkillGenericLearnt": 0,
    "SkillGenericCombat": 0,
    "Qualities": {
      "": 1
    },
    "Specialties": {
      "": 1
    },
    "VitalityMaxInjured": 0,
    "VitalityThresInjured": 0,
    "VitalityMarkInjured": "",
    "VitalityMaxMauled": 0,
    "VitalityThresMauled": 0,
    "VitalityMarkMauled": "",
    "VitalityMaxCritical": 0,
    "VitalityThresCritical": 0,
    "VitalityMarkCritical": "",
    "VitalityMaxDeadly": 0,
    "VitalityThresDeadly": 0,
    "VitalityMarkDeadly": "",
    "VitalityThresOverkill": 0,
    "VitalityMarkOverkill": "",
    "VitalityResilience": 0,
    "VitalityMarkResilience": "",
    "NemmisaryArietta": {
      "": 1
    },
    "NemmisaryNameCreed": "",
    "NemmisaryAmountCreed": 0,
    "NemmisaryNameSpite": "",
    "NemmisaryAmountSpite": 0,
    "NemmisaryLightAnima": 0,
    "NemmisaryNeutralAnima": 0,
    "NemmisaryDarkAnima": 0,
    "BroodIsBrood": false,
    "BroodSynergy": 0,
    "Inventory": {
      "Pistol": 1
    },
    "Combat": {
      "Pistol(Damage: 5, Range: M, Clip, 17)(autofire 2)": 1
    }
  },
  "PresetLibary": {}
}